fds/__init__.py
fds/sdk/__init__.py
fds/sdk/FactSetTickHistory/__init__.py
fds/sdk/FactSetTickHistory/api_client.py
fds/sdk/FactSetTickHistory/configuration.py
fds/sdk/FactSetTickHistory/exceptions.py
fds/sdk/FactSetTickHistory/model_utils.py
fds/sdk/FactSetTickHistory/rest.py
fds/sdk/FactSetTickHistory/api/__init__.py
fds/sdk/FactSetTickHistory/api/level_1_api.py
fds/sdk/FactSetTickHistory/apis/__init__.py
fds/sdk/FactSetTickHistory/model/__init__.py
fds/sdk/FactSetTickHistory/model/check_files.py
fds/sdk/FactSetTickHistory/model/completed_response.py
fds/sdk/FactSetTickHistory/model/coverage_response.py
fds/sdk/FactSetTickHistory/model/coverage_tick_history.py
fds/sdk/FactSetTickHistory/model/date_time_period.py
fds/sdk/FactSetTickHistory/model/date_time_period_min.py
fds/sdk/FactSetTickHistory/model/date_time_range.py
fds/sdk/FactSetTickHistory/model/error_example.py
fds/sdk/FactSetTickHistory/model/error_object.py
fds/sdk/FactSetTickHistory/model/factset_exchange_code.py
fds/sdk/FactSetTickHistory/model/fields.py
fds/sdk/FactSetTickHistory/model/files.py
fds/sdk/FactSetTickHistory/model/files_one.py
fds/sdk/FactSetTickHistory/model/get_files_minute_response.py
fds/sdk/FactSetTickHistory/model/get_files_response.py
fds/sdk/FactSetTickHistory/model/granularity.py
fds/sdk/FactSetTickHistory/model/level1_request_body.py
fds/sdk/FactSetTickHistory/model/levelone_request.py
fds/sdk/FactSetTickHistory/model/meta.py
fds/sdk/FactSetTickHistory/model/min_request.py
fds/sdk/FactSetTickHistory/model/min_tick_data.py
fds/sdk/FactSetTickHistory/model/minutesbar_request_body.py
fds/sdk/FactSetTickHistory/model/pagination.py
fds/sdk/FactSetTickHistory/model/status.py
fds/sdk/FactSetTickHistory/model/status_one.py
fds/sdk/FactSetTickHistory/model/submitted_response.py
fds/sdk/FactSetTickHistory/model/tick_data.py
fds/sdk/FactSetTickHistory/model/tickers.py
fds/sdk/FactSetTickHistory/model/type.py
fds/sdk/FactSetTickHistory/models/__init__.py
fds.sdk.FactSetTickHistory-1.0.3.dist-info/LICENSE
fds.sdk.FactSetTickHistory-1.0.3.dist-info/METADATA
fds.sdk.FactSetTickHistory-1.0.3.dist-info/WHEEL
fds.sdk.FactSetTickHistory-1.0.3.dist-info/top_level.txt
fds.sdk.FactSetTickHistory-1.0.3.dist-info/RECORD
